ngraph/__init__.py
ngraph/__main__.py
ngraph/_version.py
ngraph/cli.py
ngraph/explorer.py
ngraph/logging.py
ngraph/py.typed
ngraph/scenario.py
ngraph/analysis/__init__.py
ngraph/analysis/context.py
ngraph/analysis/demand.py
ngraph/analysis/failure_manager.py
ngraph/analysis/functions.py
ngraph/analysis/placement.py
ngraph/dsl/__init__.py
ngraph/dsl/loader.py
ngraph/dsl/blueprints/__init__.py
ngraph/dsl/blueprints/expand.py
ngraph/dsl/blueprints/parser.py
ngraph/dsl/expansion/__init__.py
ngraph/dsl/expansion/brackets.py
ngraph/dsl/expansion/schema.py
ngraph/dsl/expansion/variables.py
ngraph/dsl/selectors/__init__.py
ngraph/dsl/selectors/conditions.py
ngraph/dsl/selectors/normalize.py
ngraph/dsl/selectors/schema.py
ngraph/dsl/selectors/select.py
ngraph/lib/__init__.py
ngraph/lib/nx.py
ngraph/model/__init__.py
ngraph/model/components.py
ngraph/model/network.py
ngraph/model/path.py
ngraph/model/demand/__init__.py
ngraph/model/demand/builder.py
ngraph/model/demand/matrix.py
ngraph/model/demand/spec.py
ngraph/model/failure/__init__.py
ngraph/model/failure/generate.py
ngraph/model/failure/membership.py
ngraph/model/failure/parser.py
ngraph/model/failure/policy.py
ngraph/model/failure/policy_set.py
ngraph/model/failure/validation.py
ngraph/model/flow/__init__.py
ngraph/model/flow/policy_config.py
ngraph/profiling/__init__.py
ngraph/profiling/profiler.py
ngraph/results/__init__.py
ngraph/results/artifacts.py
ngraph/results/flow.py
ngraph/results/snapshot.py
ngraph/results/store.py
ngraph/schemas/__init__.py
ngraph/schemas/scenario.json
ngraph/types/__init__.py
ngraph/types/base.py
ngraph/types/dto.py
ngraph/utils/__init__.py
ngraph/utils/ids.py
ngraph/utils/output_paths.py
ngraph/utils/seed_manager.py
ngraph/utils/yaml_utils.py
ngraph/workflow/__init__.py
ngraph/workflow/base.py
ngraph/workflow/build_graph.py
ngraph/workflow/cost_power.py
ngraph/workflow/max_flow_step.py
ngraph/workflow/maximum_supported_demand_step.py
ngraph/workflow/network_stats.py
ngraph-0.17.1.dist-info/licenses/LICENSE
ngraph-0.17.1.dist-info/METADATA
ngraph-0.17.1.dist-info/WHEEL
ngraph-0.17.1.dist-info/entry_points.txt
ngraph-0.17.1.dist-info/top_level.txt
ngraph-0.17.1.dist-info/RECORD
