Metadata-Version: 2.4
Name: ngraph
Version: 0.17.1
Summary: A tool and a library for network modeling and analysis.
Author: Andrey Golovanov
License-Expression: AGPL-3.0-or-later
Project-URL: Homepage, https://github.com/networmix/NetGraph
Classifier: Development Status :: 4 - Beta
Classifier: Intended Audience :: Developers
Classifier: Intended Audience :: Science/Research
Classifier: Topic :: Scientific/Engineering
Classifier: Topic :: System :: Networking
Classifier: Topic :: Software Development :: Libraries :: Python Modules
Classifier: Programming Language :: Python :: 3
Classifier: Programming Language :: Python :: 3.11
Classifier: Programming Language :: Python :: 3.12
Classifier: Programming Language :: Python :: 3.13
Classifier: Operating System :: OS Independent
Classifier: Typing :: Typed
Requires-Python: >=3.11
License-File: LICENSE
Requires-Dist: networkx>=3.0
Requires-Dist: pyyaml>=6.0
Requires-Dist: pandas>=2.0
Requires-Dist: jsonschema>=4.0
Requires-Dist: netgraph-core>=0.3.0
Provides-Extra: dev
Requires-Dist: pytest>=8; extra == "dev"
Requires-Dist: pytest-cov; extra == "dev"
Requires-Dist: pytest-benchmark; extra == "dev"
Requires-Dist: pytest-mock; extra == "dev"
Requires-Dist: pytest-timeout; extra == "dev"
Requires-Dist: numpy; extra == "dev"
Requires-Dist: matplotlib; extra == "dev"
Requires-Dist: seaborn; extra == "dev"
Requires-Dist: mkdocs-material; extra == "dev"
Requires-Dist: pdoc; extra == "dev"
Requires-Dist: ruff==0.11.13; extra == "dev"
Requires-Dist: pyright==1.1.401; extra == "dev"
Requires-Dist: pandas-stubs; extra == "dev"
Requires-Dist: pre-commit; extra == "dev"
Requires-Dist: build; extra == "dev"
Requires-Dist: twine; extra == "dev"
Requires-Dist: jsonschema; extra == "dev"
Dynamic: license-file
